{
  "docs": {
    "Employees": ["doc2"],
    "Employment & Movement": [
      {
        "type" : "subcategory",
        "label" : "Timekeeping",
        "ids" : ["importAttendance","doc11","leaveapp","obapp","otapp","holidayworkapp","restdayworkapp","timelogcorrections","offsetApp","timeAdj","undertimeApp","waiveUndertimeApp"]
         
        },
        {
          "type" : "subcategory",
          "label" : "Payroll",
          "ids" : ["doc9"]
           
        },
        {
          "type" : "subcategory",
          "label" : "Leaves",
          "ids" : ["leaveEnrollment"]
          
        }
      ],
    "Departing": ["finalpay"],
    "Year End Processing": ["yearend"],
    "Reports": ["empreports","dtrreports","payrollreports","alphalistReports"],
    "Setup": [ 
      {
        "type" : "subcategory",
        "label" : "Salaries",
        "ids" : ["salariessetup","doc10"]
        
        },
        {
          "type" : "subcategory",
          "label" : "Band Level/Job Grade",
          "ids" : ["bandlevel"]
          
        },
        {
          "type" : "subcategory",
          "label" : "Policies",
          "ids" : ["doc3"]
          
        },
        {
          "type" : "subcategory",
          "label" : "Rates",
          "ids" : ["rates"]
          
        },
        {
          "type" : "subcategory",
          "label" : "Government Benefits and Factors",
          "ids" : ["govben"]
          
        },
        {
          "type" : "subcategory",
          "label" : "Cut-Off Dates and Pay Periods",
          "ids" : ["payperiod"]
          
        },
        {
          "type" : "subcategory",
          "label" : "Benefit Entitlement",
          "ids" : ["benefit", "benefitentitlement"]
          
        },
        {
          "type" : "subcategory",
          "label" : "Leaves",
          "ids" : ["leavetype","leaveconfig","leaveentitlement"]
          
        },
        {
          "type" : "subcategory",
          "label" : "Loans",
          "ids" : ["loantypes","loanentitle"]
        
        },
        {
          "type" : "subcategory",
          "label" : "Allowance",
          "ids" : ["allowancetype","allowanceent"]
        
        },
        {
          "type" : "subcategory",
          "label" : "Work Schedules",
          "ids" : ["doc12"]
        
        },
        {
          "type" : "subcategory",
          "label" : "Calendars",
          "ids" : ["addCalendar","importCalendar"]
          
        },
        {
          "type" : "subcategory",
          "label" : "Holiday",
          "ids" : ["holiday"]
          
        },     
        {
          "type" : "subcategory",
          "label" : "Roles & Permissions",
          "ids" : ["roles"]
          
        },
        {
          "type" : "subcategory",
          "label" : "Users",
          "ids" : ["users"]
          
        }
    ],
    "Organization":["company","divdept","division","location","customGroup","pos","job"]


  },
  "docs-other": {
    "First Category": ["doc4", "doc5"]
  }
}